neurosnap/__init__.py
neurosnap/api.py
neurosnap/chemicals.py
neurosnap/conformers.py
neurosnap/log.py
neurosnap/msa.py
neurosnap/protein.py
neurosnap/algos/alphafold.py
neurosnap/algos/clusterprot.py
neurosnap/algos/lDDT.py
neurosnap-0.0.64.dist-info/LICENSE
neurosnap-0.0.64.dist-info/METADATA
neurosnap-0.0.64.dist-info/WHEEL
neurosnap-0.0.64.dist-info/top_level.txt
neurosnap-0.0.64.dist-info/RECORD
