Metadata-Version: 2.1
Name: neurosnap
Version: 0.0.64
Summary: Collection of useful bioinformatic functions and tools for various computational biology pipelines.
Author: Keaun Amani
License: Attribution 4.0 International
Project-URL: Homepage, https://github.com/NeurosnapInc/neurosnap
Project-URL: Issues, https://github.com/NeurosnapInc/neurosnap/issues
Classifier: Programming Language :: Python :: 3
Classifier: Operating System :: OS Independent
Classifier: Development Status :: 3 - Alpha
Requires-Python: >=3.8
License-File: LICENSE
Requires-Dist: requests >2
Requires-Dist: numpy >1.0.0
Requires-Dist: pandas
Requires-Dist: biopython
Requires-Dist: rdkit
Requires-Dist: scipy
Requires-Dist: matplotlib
Requires-Dist: tabulate
Requires-Dist: requests-toolbelt
Provides-Extra: dev
Requires-Dist: ruff ==0.7.0 ; extra == 'dev'
Requires-Dist: sphinx ==8.1.3 ; extra == 'dev'
Requires-Dist: sphinx-rtd-theme ==3.0.1 ; extra == 'dev'
Requires-Dist: sphinx-autodoc-typehints ==2.5.0 ; extra == 'dev'
